{"info":{"_postman_id":"5f9f8686-4703-4912-afda-72554989f6c4","name":"POST","schema":"https://schema.getpostman.com/json/collection/v2.1.0/collection.json"},"item":[{"name":"Post user","id":"8cf00009-6873-4fd8-ae69-bba9c0c1a0f8","protocolProfileBehavior":{"disableBodyPruning":true},"request":{"method":"POST","header":[],"body":{"mode":"raw","raw":"{\n    \"name\": \"morpheus\",\n    \"job\": \"leader\"\n}"},"url":{"raw":"https://reqres.in/api/users","protocol":"https","host":["reqres","in"],"path":["api","users"]}},"response":[]},{"name":"Post user cyrillic NO VALIDATION","id":"218224ba-4d1b-4ab2-a9fa-49276affab0b","protocolProfileBehavior":{"disableBodyPruning":true},"request":{"method":"POST","header":[],"body":{"mode":"raw","raw":"{\n    \"name\": \"Василий\",\n    \"job\": \"leader\"\n}"},"url":{"raw":"https://reqres.in/api/users","protocol":"https","host":["reqres","in"],"path":["api","users"]}},"response":[]},{"name":"Post user special symbols NO VALIDATION","id":"012d63e2-83a6-46ad-bf4f-6dc0a04d4081","protocolProfileBehavior":{"disableBodyPruning":true},"request":{"method":"POST","header":[],"body":{"mode":"raw","raw":"{\n    \"name\": \"№3@@@\",\n    \"job\": \"leader\"\n}"},"url":{"raw":"https://reqres.in/api/users?page=3","protocol":"https","host":["reqres","in"],"path":["api","users"],"query":[{"key":"page","value":"3"}]}},"response":[]},{"name":"Post user empty fields NO VALIDATION","id":"54a39317-e76c-4785-88a1-adf69807dd37","protocolProfileBehavior":{"disableBodyPruning":true},"request":{"method":"POST","header":[],"url":{"raw":"https://reqres.in/api/users","protocol":"https","host":["reqres","in"],"path":["api","users"]}},"response":[]}]}